.DS_Store
pypairs/__init__.py
pypairs/cyclone.py
pypairs/helper.py
pypairs/sandbag.py
pypairs/test.py
pypairs/wrapper.py
pypairs-2.0.6.dist-info/LICENSE
pypairs-2.0.6.dist-info/METADATA
pypairs-2.0.6.dist-info/WHEEL
pypairs-2.0.6.dist-info/top_level.txt
pypairs-2.0.6.dist-info/RECORD
