Metadata-Version: 2.1
Name: pypairs
Version: 2.0.6
Summary: A Python-reimplementation of the Pairs algorithm described by A. Scialdone et al. (2015)
Home-page: https://github.com/rfechtner/pypairs
Author: Ron Fechtner
Author-email: ronfechtner@gmail.com
License: https://github.com/rfechtner/pypairs/blob/master/LICENSE
Project-URL: Original Paper, http://dx.doi.org/10.1016/j.ymeth.2015.06.021
Project-URL: GitHub URL, https://github.com/rfechtner/pypairs
Keywords: scRNA classifier machine-learning marker pairs
Platform: UNKNOWN
Classifier: Development Status :: 4 - Beta
Classifier: Intended Audience :: Science/Research
Classifier: Topic :: Scientific/Engineering :: Bio-Informatics
Classifier: License :: OSI Approved :: MIT License
Classifier: Programming Language :: Python :: 3 :: Only
Requires-Dist: numpy
Requires-Dist: pandas
Requires-Dist: numba
Requires-Dist: colorama
Provides-Extra: plot
Requires-Dist: mathplotlib; extra == 'plot'
